{
    "fs": [
        {
            "host": "This PC",
            "file_path": "/Users/prathameshyadav/ARC-Hawk/testdata/ground_truth/credit_cards.json",
            "pattern_name": "Credit Card",
            "matches": [
                "6011111111111117",
                "378282246310005",
                "4532015112830366",
                "4111111111111111",
                "5555555555554444",
                "4532015112830367",
                "5425233430109903",
                "3530111333300000"
            ],
            "sample_text": "[\n    {\n        \"value\": \"4532015112830366\",\n     ",
            "profile": "test_scan",
            "data_source": "fs",
            "file_data": {
                "absolute_path": "/Users/prathameshyadav/ARC-Hawk/testdata/ground_truth/credit_cards.json",
                "filename": "credit_cards.json",
                "extension": ".json",
                "size_bytes": 1787,
                "permissions_octal": "644",
                "owner": "prathameshyadav",
                "group": "staff",
                "created_time": "2025-12-30 12:34:09",
                "modified_time": "2025-12-30 12:34:09",
                "accessed_time": "2025-12-30 18:18:25"
            },
            "severity": "Medium",
            "severity_description": "Detected more than 5 PII or Secrets"
        },
        {
            "host": "This PC",
            "file_path": "/Users/prathameshyadav/ARC-Hawk/testdata/ground_truth/credit_cards.json",
            "pattern_name": "Aadhar",
            "matches": [
                "123456789012"
            ],
            "sample_text": "[\n    {\n        \"value\": \"4532015112830366\",\n     ",
            "profile": "test_scan",
            "data_source": "fs",
            "file_data": {
                "absolute_path": "/Users/prathameshyadav/ARC-Hawk/testdata/ground_truth/credit_cards.json",
                "filename": "credit_cards.json",
                "extension": ".json",
                "size_bytes": 1787,
                "permissions_octal": "644",
                "owner": "prathameshyadav",
                "group": "staff",
                "created_time": "2025-12-30 12:34:09",
                "modified_time": "2025-12-30 12:34:09",
                "accessed_time": "2025-12-30 18:18:25"
            },
            "severity": "Low",
            "severity_description": "Detected less than 5 PII or Secrets"
        },
        {
            "host": "This PC",
            "file_path": "/Users/prathameshyadav/ARC-Hawk/testdata/ground_truth/negative_samples.json",
            "pattern_name": "Aadhar",
            "matches": [
                "446655440000"
            ],
            "sample_text": "[\n    {\n        \"value\": \"192.168.1.1\",\n        \"e",
            "profile": "test_scan",
            "data_source": "fs",
            "file_data": {
                "absolute_path": "/Users/prathameshyadav/ARC-Hawk/testdata/ground_truth/negative_samples.json",
                "filename": "negative_samples.json",
                "extension": ".json",
                "size_bytes": 2457,
                "permissions_octal": "644",
                "owner": "prathameshyadav",
                "group": "staff",
                "created_time": "2025-12-30 12:34:42",
                "modified_time": "2025-12-30 12:34:42",
                "accessed_time": "2025-12-30 18:18:25"
            },
            "severity": "Low",
            "severity_description": "Detected less than 5 PII or Secrets"
        },
        {
            "host": "This PC",
            "file_path": "/Users/prathameshyadav/ARC-Hawk/testdata/ground_truth/aadhaar_numbers.json",
            "pattern_name": "Aadhar",
            "matches": [
                "234123456789",
                "111111111111",
                "000000000000",
                "987654321098",
                "123412345670"
            ],
            "sample_text": "[\n    {\n        \"value\": \"234123456789\",\n        \"",
            "profile": "test_scan",
            "data_source": "fs",
            "file_data": {
                "absolute_path": "/Users/prathameshyadav/ARC-Hawk/testdata/ground_truth/aadhaar_numbers.json",
                "filename": "aadhaar_numbers.json",
                "extension": ".json",
                "size_bytes": 1375,
                "permissions_octal": "644",
                "owner": "prathameshyadav",
                "group": "staff",
                "created_time": "2025-12-30 12:34:40",
                "modified_time": "2025-12-30 12:34:40",
                "accessed_time": "2025-12-30 18:18:25"
            },
            "severity": "Low",
            "severity_description": "Detected less than 5 PII or Secrets"
        },
        {
            "host": "This PC",
            "file_path": "/Users/prathameshyadav/ARC-Hawk/testdata/ground_truth/samples.json",
            "pattern_name": "Email",
            "matches": [
                "test_user@mail-server.io",
                "alice.smith@company.org",
                "user+tag@example.co.uk",
                "john.doe@example.com",
                "name@example.com",
                "admin@localhost.dev"
            ],
            "sample_text": "[\n  {\n    \"value\": \"4532015112830366\",\n    \"expect",
            "profile": "test_scan",
            "data_source": "fs",
            "file_data": {
                "absolute_path": "/Users/prathameshyadav/ARC-Hawk/testdata/ground_truth/samples.json",
                "filename": "samples.json",
                "extension": ".json",
                "size_bytes": 9433,
                "permissions_octal": "644",
                "owner": "prathameshyadav",
                "group": "staff",
                "created_time": "2025-12-30 12:34:53",
                "modified_time": "2025-12-30 12:34:53",
                "accessed_time": "2025-12-30 18:18:25"
            },
            "severity": "Medium",
            "severity_description": "Detected more than 5 PII or Secrets"
        },
        {
            "host": "This PC",
            "file_path": "/Users/prathameshyadav/ARC-Hawk/testdata/ground_truth/samples.json",
            "pattern_name": "Credit Card",
            "matches": [
                "6011111111111117",
                "378282246310005",
                "4532015112830366",
                "4111111111111111",
                "5555555555554444",
                "4532015112830367",
                "5425233430109903",
                "3530111333300000"
            ],
            "sample_text": "[\n  {\n    \"value\": \"4532015112830366\",\n    \"expect",
            "profile": "test_scan",
            "data_source": "fs",
            "file_data": {
                "absolute_path": "/Users/prathameshyadav/ARC-Hawk/testdata/ground_truth/samples.json",
                "filename": "samples.json",
                "extension": ".json",
                "size_bytes": 9433,
                "permissions_octal": "644",
                "owner": "prathameshyadav",
                "group": "staff",
                "created_time": "2025-12-30 12:34:53",
                "modified_time": "2025-12-30 12:34:53",
                "accessed_time": "2025-12-30 18:18:25"
            },
            "severity": "Medium",
            "severity_description": "Detected more than 5 PII or Secrets"
        },
        {
            "host": "This PC",
            "file_path": "/Users/prathameshyadav/ARC-Hawk/testdata/ground_truth/samples.json",
            "pattern_name": "Aadhar",
            "matches": [
                "234123456789",
                "111111111111",
                "000000000000",
                "123456789012",
                "987654321098",
                "123412345670",
                "446655440000"
            ],
            "sample_text": "[\n  {\n    \"value\": \"4532015112830366\",\n    \"expect",
            "profile": "test_scan",
            "data_source": "fs",
            "file_data": {
                "absolute_path": "/Users/prathameshyadav/ARC-Hawk/testdata/ground_truth/samples.json",
                "filename": "samples.json",
                "extension": ".json",
                "size_bytes": 9433,
                "permissions_octal": "644",
                "owner": "prathameshyadav",
                "group": "staff",
                "created_time": "2025-12-30 12:34:53",
                "modified_time": "2025-12-30 12:34:53",
                "accessed_time": "2025-12-30 18:18:25"
            },
            "severity": "Medium",
            "severity_description": "Detected more than 5 PII or Secrets"
        },
        {
            "host": "This PC",
            "file_path": "/Users/prathameshyadav/ARC-Hawk/testdata/ground_truth/samples.json",
            "pattern_name": "PAN",
            "matches": [
                "AFZPK7190K",
                "ABCDE1234F",
                "abcde1234f",
                "CQHPS4560M",
                "BNZAA2318J",
                "AAAAA9999A"
            ],
            "sample_text": "[\n  {\n    \"value\": \"4532015112830366\",\n    \"expect",
            "profile": "test_scan",
            "data_source": "fs",
            "file_data": {
                "absolute_path": "/Users/prathameshyadav/ARC-Hawk/testdata/ground_truth/samples.json",
                "filename": "samples.json",
                "extension": ".json",
                "size_bytes": 9433,
                "permissions_octal": "644",
                "owner": "prathameshyadav",
                "group": "staff",
                "created_time": "2025-12-30 12:34:53",
                "modified_time": "2025-12-30 12:34:53",
                "accessed_time": "2025-12-30 18:18:25"
            },
            "severity": "Medium",
            "severity_description": "Detected more than 5 PII or Secrets"
        },
        {
            "host": "This PC",
            "file_path": "/Users/prathameshyadav/ARC-Hawk/testdata/ground_truth/README.md",
            "pattern_name": "Credit Card",
            "matches": [
                "4532015112830366"
            ],
            "sample_text": "# Ground Truth Testing Guide\n\n## Purpose\nThis dire",
            "profile": "test_scan",
            "data_source": "fs",
            "file_data": {
                "absolute_path": "/Users/prathameshyadav/ARC-Hawk/testdata/ground_truth/README.md",
                "filename": "README.md",
                "extension": ".md",
                "size_bytes": 3428,
                "permissions_octal": "644",
                "owner": "prathameshyadav",
                "group": "staff",
                "created_time": "2025-12-30 12:06:56",
                "modified_time": "2025-12-30 12:06:56",
                "accessed_time": "2025-12-30 18:18:25"
            },
            "severity": "Low",
            "severity_description": "Detected less than 5 PII or Secrets"
        },
        {
            "host": "This PC",
            "file_path": "/Users/prathameshyadav/ARC-Hawk/testdata/ground_truth/emails.json",
            "pattern_name": "Email",
            "matches": [
                "test_user@mail-server.io",
                "alice.smith@company.org",
                "user+tag@example.co.uk",
                "john.doe@example.com",
                "name@example.com",
                "admin@localhost.dev"
            ],
            "sample_text": "[\n    {\n        \"value\": \"john.doe@example.com\",\n ",
            "profile": "test_scan",
            "data_source": "fs",
            "file_data": {
                "absolute_path": "/Users/prathameshyadav/ARC-Hawk/testdata/ground_truth/emails.json",
                "filename": "emails.json",
                "extension": ".json",
                "size_bytes": 1791,
                "permissions_octal": "644",
                "owner": "prathameshyadav",
                "group": "staff",
                "created_time": "2025-12-30 12:34:18",
                "modified_time": "2025-12-30 12:34:18",
                "accessed_time": "2025-12-30 18:18:25"
            },
            "severity": "Medium",
            "severity_description": "Detected more than 5 PII or Secrets"
        },
        {
            "host": "This PC",
            "file_path": "/Users/prathameshyadav/ARC-Hawk/testdata/ground_truth/negative_samples.md",
            "pattern_name": "Phone Number",
            "matches": [
                "000) 000-0000"
            ],
            "sample_text": "# Ground Truth Dataset - Negative Samples (Non-PII",
            "profile": "test_scan",
            "data_source": "fs",
            "file_data": {
                "absolute_path": "/Users/prathameshyadav/ARC-Hawk/testdata/ground_truth/negative_samples.md",
                "filename": "negative_samples.md",
                "extension": ".md",
                "size_bytes": 1744,
                "permissions_octal": "644",
                "owner": "prathameshyadav",
                "group": "staff",
                "created_time": "2025-12-30 12:06:18",
                "modified_time": "2025-12-30 12:06:18",
                "accessed_time": "2025-12-30 18:18:25"
            },
            "severity": "Low",
            "severity_description": "Detected less than 5 PII or Secrets"
        },
        {
            "host": "This PC",
            "file_path": "/Users/prathameshyadav/ARC-Hawk/testdata/ground_truth/negative_samples.md",
            "pattern_name": "Credit Card",
            "matches": [
                "5555666677778888"
            ],
            "sample_text": "# Ground Truth Dataset - Negative Samples (Non-PII",
            "profile": "test_scan",
            "data_source": "fs",
            "file_data": {
                "absolute_path": "/Users/prathameshyadav/ARC-Hawk/testdata/ground_truth/negative_samples.md",
                "filename": "negative_samples.md",
                "extension": ".md",
                "size_bytes": 1744,
                "permissions_octal": "644",
                "owner": "prathameshyadav",
                "group": "staff",
                "created_time": "2025-12-30 12:06:18",
                "modified_time": "2025-12-30 12:06:18",
                "accessed_time": "2025-12-30 18:18:25"
            },
            "severity": "Low",
            "severity_description": "Detected less than 5 PII or Secrets"
        },
        {
            "host": "This PC",
            "file_path": "/Users/prathameshyadav/ARC-Hawk/testdata/ground_truth/negative_samples.md",
            "pattern_name": "Aadhar",
            "matches": [
                "123456789123",
                "987654321987",
                "111111111111",
                "000000000000",
                "123456789012",
                "012345678905"
            ],
            "sample_text": "# Ground Truth Dataset - Negative Samples (Non-PII",
            "profile": "test_scan",
            "data_source": "fs",
            "file_data": {
                "absolute_path": "/Users/prathameshyadav/ARC-Hawk/testdata/ground_truth/negative_samples.md",
                "filename": "negative_samples.md",
                "extension": ".md",
                "size_bytes": 1744,
                "permissions_octal": "644",
                "owner": "prathameshyadav",
                "group": "staff",
                "created_time": "2025-12-30 12:06:18",
                "modified_time": "2025-12-30 12:06:18",
                "accessed_time": "2025-12-30 18:18:25"
            },
            "severity": "Medium",
            "severity_description": "Detected more than 5 PII or Secrets"
        },
        {
            "host": "This PC",
            "file_path": "/Users/prathameshyadav/ARC-Hawk/testdata/ground_truth/aadhaar_numbers.md",
            "pattern_name": "Aadhar",
            "matches": [
                "678567890123",
                "345234567890",
                "456345678902",
                "234123456789",
                "234123456788",
                "111111111111",
                "000000000000",
                "567456789012",
                "999999999999",
                "123456789012",
                "345234567891",
                "987654321098",
                "012345678901",
                "456345678901",
                "2341-2345-6789"
            ],
            "sample_text": "# Ground Truth Dataset - Aadhaar Numbers\n\n## Purpo",
            "profile": "test_scan",
            "data_source": "fs",
            "file_data": {
                "absolute_path": "/Users/prathameshyadav/ARC-Hawk/testdata/ground_truth/aadhaar_numbers.md",
                "filename": "aadhaar_numbers.md",
                "extension": ".md",
                "size_bytes": 1571,
                "permissions_octal": "644",
                "owner": "prathameshyadav",
                "group": "staff",
                "created_time": "2025-12-30 12:05:38",
                "modified_time": "2025-12-30 12:05:38",
                "accessed_time": "2025-12-30 18:18:25"
            },
            "severity": "High",
            "severity_description": "Detected more than 10 PII or Secrets"
        },
        {
            "host": "This PC",
            "file_path": "/Users/prathameshyadav/ARC-Hawk/testdata/ground_truth/emails.md",
            "pattern_name": "Email",
            "matches": [
                "jane_smith@company.org",
                "_user@example.com",
                "email@subdomain.example.com",
                "johndoe@gmail.com",
                "john.doe@example.com",
                "firstname.lastname@example.com",
                "contact@sub.domain.com",
                "name@example.com",
                "info@example.io",
                "user+tag@gmail.com",
                "very.unusual.@.unusual.com",
                "john.doe@gmail.com",
                "1234567890@example.com",
                "user123@domain.co.uk"
            ],
            "sample_text": "# Ground Truth Dataset - Email Addresses\n\n## Purpo",
            "profile": "test_scan",
            "data_source": "fs",
            "file_data": {
                "absolute_path": "/Users/prathameshyadav/ARC-Hawk/testdata/ground_truth/emails.md",
                "filename": "emails.md",
                "extension": ".md",
                "size_bytes": 1303,
                "permissions_octal": "644",
                "owner": "prathameshyadav",
                "group": "staff",
                "created_time": "2025-12-30 12:05:01",
                "modified_time": "2025-12-30 12:05:01",
                "accessed_time": "2025-12-30 18:18:25"
            },
            "severity": "High",
            "severity_description": "Detected more than 10 PII or Secrets"
        },
        {
            "host": "This PC",
            "file_path": "/Users/prathameshyadav/ARC-Hawk/testdata/ground_truth/emails.md",
            "pattern_name": "Phone Number",
            "matches": [
                "1234567890"
            ],
            "sample_text": "# Ground Truth Dataset - Email Addresses\n\n## Purpo",
            "profile": "test_scan",
            "data_source": "fs",
            "file_data": {
                "absolute_path": "/Users/prathameshyadav/ARC-Hawk/testdata/ground_truth/emails.md",
                "filename": "emails.md",
                "extension": ".md",
                "size_bytes": 1303,
                "permissions_octal": "644",
                "owner": "prathameshyadav",
                "group": "staff",
                "created_time": "2025-12-30 12:05:01",
                "modified_time": "2025-12-30 12:05:01",
                "accessed_time": "2025-12-30 18:18:25"
            },
            "severity": "Low",
            "severity_description": "Detected less than 5 PII or Secrets"
        },
        {
            "host": "This PC",
            "file_path": "/Users/prathameshyadav/ARC-Hawk/testdata/ground_truth/credit_cards.md",
            "pattern_name": "Credit Card",
            "matches": [
                "4024007198964305",
                "371449635398431",
                "6011111111111117",
                "378282246310005",
                "6011000990139424",
                "6011601160116611",
                "6011111111111118",
                "378734493671000",
                "4916338506082832",
                "4532015112830366",
                "378282246310006",
                "5555555555554444",
                "5425233430109904",
                "4532015112830367",
                "5425233430109903"
            ],
            "sample_text": "# Ground Truth Dataset - Credit Cards\n\n## Purpose\n",
            "profile": "test_scan",
            "data_source": "fs",
            "file_data": {
                "absolute_path": "/Users/prathameshyadav/ARC-Hawk/testdata/ground_truth/credit_cards.md",
                "filename": "credit_cards.md",
                "extension": ".md",
                "size_bytes": 1328,
                "permissions_octal": "644",
                "owner": "prathameshyadav",
                "group": "staff",
                "created_time": "2025-12-30 12:04:50",
                "modified_time": "2025-12-30 12:04:50",
                "accessed_time": "2025-12-30 18:18:25"
            },
            "severity": "High",
            "severity_description": "Detected more than 10 PII or Secrets"
        },
        {
            "host": "This PC",
            "file_path": "/Users/prathameshyadav/ARC-Hawk/testdata/ground_truth/credit_cards.md",
            "pattern_name": "Aadhar",
            "matches": [
                "4532-0151-1283"
            ],
            "sample_text": "# Ground Truth Dataset - Credit Cards\n\n## Purpose\n",
            "profile": "test_scan",
            "data_source": "fs",
            "file_data": {
                "absolute_path": "/Users/prathameshyadav/ARC-Hawk/testdata/ground_truth/credit_cards.md",
                "filename": "credit_cards.md",
                "extension": ".md",
                "size_bytes": 1328,
                "permissions_octal": "644",
                "owner": "prathameshyadav",
                "group": "staff",
                "created_time": "2025-12-30 12:04:50",
                "modified_time": "2025-12-30 12:04:50",
                "accessed_time": "2025-12-30 18:18:25"
            },
            "severity": "Low",
            "severity_description": "Detected less than 5 PII or Secrets"
        },
        {
            "host": "This PC",
            "file_path": "/Users/prathameshyadav/ARC-Hawk/testdata/ground_truth/pan_numbers.md",
            "pattern_name": "PAN",
            "matches": [
                "ABCDE1234C",
                "ABCPL1234L",
                "LMNOP5678F",
                "MNOPQ9012C",
                "ABCPC1234C",
                "ABCPF1234F",
                "ABCDE1234H",
                "ABCPH1234H",
                "UVWXY9012L",
                "AbCdE1234F",
                "XYZKL5678C",
                "ABCPP1234F",
                "abcde1234f",
                "PQRST5678K",
                "ABCDE1234F",
                "ABCPT1234T",
                "XYZKL5678T",
                "ABCPG1234G",
                "PQRST5678H",
                "ABCDE1234T"
            ],
            "sample_text": "# Ground Truth Dataset - Indian PAN\n\n## Purpose\nVa",
            "profile": "test_scan",
            "data_source": "fs",
            "file_data": {
                "absolute_path": "/Users/prathameshyadav/ARC-Hawk/testdata/ground_truth/pan_numbers.md",
                "filename": "pan_numbers.md",
                "extension": ".md",
                "size_bytes": 1416,
                "permissions_octal": "644",
                "owner": "prathameshyadav",
                "group": "staff",
                "created_time": "2025-12-30 12:05:13",
                "modified_time": "2025-12-30 12:05:13",
                "accessed_time": "2025-12-30 18:18:25"
            },
            "severity": "High",
            "severity_description": "Detected more than 10 PII or Secrets"
        },
        {
            "host": "This PC",
            "file_path": "/Users/prathameshyadav/ARC-Hawk/testdata/ground_truth/pan_numbers.json",
            "pattern_name": "PAN",
            "matches": [
                "AFZPK7190K",
                "ABCDE1234F",
                "abcde1234f",
                "CQHPS4560M",
                "BNZAA2318J",
                "AAAAA9999A"
            ],
            "sample_text": "[\n    {\n        \"value\": \"ABCDE1234F\",\n        \"ex",
            "profile": "test_scan",
            "data_source": "fs",
            "file_data": {
                "absolute_path": "/Users/prathameshyadav/ARC-Hawk/testdata/ground_truth/pan_numbers.json",
                "filename": "pan_numbers.json",
                "extension": ".json",
                "size_bytes": 1646,
                "permissions_octal": "644",
                "owner": "prathameshyadav",
                "group": "staff",
                "created_time": "2025-12-30 12:34:24",
                "modified_time": "2025-12-30 12:34:24",
                "accessed_time": "2025-12-30 18:18:25"
            },
            "severity": "Medium",
            "severity_description": "Detected more than 5 PII or Secrets"
        },
        {
            "host": "This PC",
            "file_path": "/Users/prathameshyadav/ARC-Hawk/testdata/ground_truth/ssn_numbers.md",
            "pattern_name": "Phone Number",
            "matches": [
                "1234567890"
            ],
            "sample_text": "# Ground Truth Dataset - US SSN\n\n## Purpose\nValida",
            "profile": "test_scan",
            "data_source": "fs",
            "file_data": {
                "absolute_path": "/Users/prathameshyadav/ARC-Hawk/testdata/ground_truth/ssn_numbers.md",
                "filename": "ssn_numbers.md",
                "extension": ".md",
                "size_bytes": 1776,
                "permissions_octal": "644",
                "owner": "prathameshyadav",
                "group": "staff",
                "created_time": "2025-12-30 12:05:22",
                "modified_time": "2025-12-30 12:05:22",
                "accessed_time": "2025-12-30 18:18:25"
            },
            "severity": "Low",
            "severity_description": "Detected less than 5 PII or Secrets"
        },
        {
            "host": "This PC",
            "file_path": "/Users/prathameshyadav/ARC-Hawk/testdata/ground_truth/ssn_numbers.md",
            "pattern_name": "SSN",
            "matches": [
                "123-45-6789"
            ],
            "sample_text": "# Ground Truth Dataset - US SSN\n\n## Purpose\nValida",
            "profile": "test_scan",
            "data_source": "fs",
            "file_data": {
                "absolute_path": "/Users/prathameshyadav/ARC-Hawk/testdata/ground_truth/ssn_numbers.md",
                "filename": "ssn_numbers.md",
                "extension": ".md",
                "size_bytes": 1776,
                "permissions_octal": "644",
                "owner": "prathameshyadav",
                "group": "staff",
                "created_time": "2025-12-30 12:05:22",
                "modified_time": "2025-12-30 12:05:22",
                "accessed_time": "2025-12-30 18:18:25"
            },
            "severity": "Low",
            "severity_description": "Detected less than 5 PII or Secrets"
        }
    ]
}